pubsub_meta/__init__.py
pubsub_meta/__main__.py
pubsub_meta/cli.py
pubsub_meta-0.0.1.dist-info/LICENSE
pubsub_meta-0.0.1.dist-info/METADATA
pubsub_meta-0.0.1.dist-info/WHEEL
pubsub_meta-0.0.1.dist-info/entry_points.txt
pubsub_meta-0.0.1.dist-info/top_level.txt
pubsub_meta-0.0.1.dist-info/RECORD
