Metadata-Version: 2.1
Name: pubsub-meta
Version: 0.0.1
Summary: Pub/Sub metadata viewer
Home-page: https://github.com/martintupy/pubsub-meta
Author: Martin Tupy
Author-email: id@martintupy.com
License: Apache-2.0
Classifier: License :: OSI Approved :: Apache Software License
Classifier: Programming Language :: Python :: 3
Classifier: Programming Language :: Python :: 3 :: Only
Classifier: Programming Language :: Python :: 3.6
Classifier: Programming Language :: Python :: 3.7
Classifier: Programming Language :: Python :: 3.8
Classifier: Programming Language :: Python :: 3.9
Classifier: Programming Language :: Python :: 3.10
Requires-Python: >=3.6
License-File: LICENSE
Requires-Dist: Click
Requires-Dist: google-auth-oauthlib
Requires-Dist: pyyaml
Requires-Dist: rich
Requires-Dist: readchar
